pyandroid/__init__.py
pyandroid/__version__.py
pyandroid/core.py
pyandroid/py.typed
pyandroid/ui.py
pyandroid/utils.py
pyandroid/backend/__init__.py
pyandroid/backend/kivy_backend.py
pyandroid_dev-1.4.0.dist-info/licenses/LICENSE
pyandroid_dev-1.4.0.dist-info/METADATA
pyandroid_dev-1.4.0.dist-info/WHEEL
pyandroid_dev-1.4.0.dist-info/top_level.txt
pyandroid_dev-1.4.0.dist-info/RECORD
