Metadata-Version: 2.4
Name: pyandroid-dev
Version: 1.4.0
Summary: A comprehensive Python library for creating Android-like applications with GUI support, improved error handling, and full type hints.
Home-page: https://github.com/subhobhai943/pyandroid-dev
Author: Subhobhai
Author-email: Subhobhai <sarkarsubhadip604@gmail.com>
License: PyAndroid Custom License v1.0
Project-URL: Homepage, https://github.com/subhobhai943/pyandroid-dev
Project-URL: Bug Reports, https://github.com/subhobhai943/pyandroid-dev/issues
Project-URL: Source, https://github.com/subhobhai943/pyandroid-dev
Project-URL: Documentation, https://github.com/subhobhai943/pyandroid-dev/tree/main/docs
Keywords: android,mobile,app,development,kivy,gui,cross-platform,framework
Classifier: Development Status :: 4 - Beta
Classifier: Intended Audience :: Developers
Classifier: Topic :: Software Development :: Libraries :: Python Modules
Classifier: Topic :: Software Development :: User Interfaces
Classifier: License :: Other/Proprietary License
Classifier: Programming Language :: Python :: 3
Classifier: Programming Language :: Python :: 3.8
Classifier: Programming Language :: Python :: 3.9
Classifier: Programming Language :: Python :: 3.10
Classifier: Programming Language :: Python :: 3.11
Classifier: Programming Language :: Python :: 3.12
Classifier: Operating System :: OS Independent
Classifier: Environment :: Console
Classifier: Environment :: X11 Applications
Classifier: Typing :: Typed
Requires-Python: >=3.7
License-File: LICENSE
Provides-Extra: gui
Requires-Dist: kivy>=2.0.0; extra == "gui"
Provides-Extra: dev
Requires-Dist: pytest>=7.0.0; extra == "dev"
Requires-Dist: pytest-cov>=4.0.0; extra == "dev"
Requires-Dist: black>=22.0.0; extra == "dev"
Requires-Dist: flake8>=6.0.0; extra == "dev"
Requires-Dist: mypy>=1.0.0; extra == "dev"
Provides-Extra: all
Requires-Dist: kivy>=2.0.0; extra == "all"
Requires-Dist: pytest>=7.0.0; extra == "all"
Requires-Dist: pytest-cov>=4.0.0; extra == "all"
Dynamic: author
Dynamic: home-page
Dynamic: license-file
Dynamic: requires-python
